odenmark/__init__.py
odenmark/checker.py
odenmark-0.1.1.dist-info/licenses/LICENSE.txt
odenmark-0.1.1.dist-info/METADATA
odenmark-0.1.1.dist-info/WHEEL
odenmark-0.1.1.dist-info/top_level.txt
odenmark-0.1.1.dist-info/RECORD
