Metadata-Version: 2.4
Name: odenmark
Version: 0.1.1
Summary: A simple odd/even checker library.
Author-email: JIYO P V <jiyopv21@gmail.com>
Project-URL: Homepage, https://github.com/jiyo-pv/odenmark
Requires-Python: >=3.7
License-File: LICENSE.txt
Dynamic: license-file
